yaru/__init__.py
yaru/argument.py
yaru/command.py
yaru/context.py
yaru/exceptions.py
yaru-0.2.0.dist-info/METADATA
yaru-0.2.0.dist-info/WHEEL
yaru-0.2.0.dist-info/entry_points.txt
yaru-0.2.0.dist-info/licenses/LICENSE
yaru-0.2.0.dist-info/RECORD
