Metadata-Version: 2.4
Name: yaru
Version: 0.2.0
Summary: Write and manage your project's development scripts with modern Python syntax
Project-URL: Homepage, https://github.com/c0dearm/yaru
Project-URL: Documentation, https://github.com/c0dearm/yaru
Project-URL: Repository, https://github.com/c0dearm/yaru
Project-URL: Issues, https://github.com/c0dearm/yaru/issues
Project-URL: Changelog, https://github.com/c0dearm/yaru
Author-email: Aitor Ruano Miralles <codearm@pm.me>
Maintainer-email: Aitor Ruano Miralles <codearm@pm.me>
License: MIT License
License-File: LICENSE
Classifier: Intended Audience :: Developers
Classifier: Intended Audience :: Information Technology
Classifier: Intended Audience :: System Administrators
Classifier: License :: OSI Approved :: MIT License
Classifier: Operating System :: OS Independent
Classifier: Programming Language :: Python
Classifier: Programming Language :: Python :: 3 :: Only
Classifier: Programming Language :: Python :: 3.12
Classifier: Programming Language :: Python :: 3.13
Classifier: Topic :: Software Development
Classifier: Topic :: Software Development :: Libraries
Classifier: Topic :: Software Development :: Libraries :: Application Frameworks
Classifier: Topic :: Software Development :: Libraries :: Python Modules
Classifier: Typing :: Typed
Requires-Python: >=3.12
